README.md
setup.py
cli/sdem
sdem/__init__.py
sdem/decorators.py
sdem/dispatch.py
sdem/experiment.py
sdem/main.py
sdem/state.py
sdem/template.py
sdem/utils.py
sdem.egg-info/PKG-INFO
sdem.egg-info/SOURCES.txt
sdem.egg-info/dependency_links.txt
sdem.egg-info/requires.txt
sdem.egg-info/top_level.txt
sdem/cli/__init__.py
sdem/cli/clean.py
sdem/cli/dvc.py
sdem/cli/install.py
sdem/cli/rollback.py
sdem/cli/run.py
sdem/cli/setup.py
sdem/cli/sync.py
sdem/cli/vis.py