Metadata-Version: 2.1
Name: sdem
Version: 0.1.1
Summary: Sacred Experiment Manager
Home-page: UNKNOWN
Author: O Hamelijnck
Author-email: ohamelijnck@gmail.com
License: UNKNOWN
Platform: UNKNOWN
Classifier: Programming Language :: Python :: 3
Classifier: License :: OSI Approved :: MIT License
Classifier: Operating System :: OS Independent
Requires-Python: >=3.6
